connect_mongo.py
setup.py
connect_mongo.egg-info/PKG-INFO
connect_mongo.egg-info/SOURCES.txt
connect_mongo.egg-info/dependency_links.txt
connect_mongo.egg-info/requires.txt
connect_mongo.egg-info/top_level.txt