Metadata-Version: 1.0
Name: connect-mongo
Version: 1.0.2
Summary: A qucik way use pymongo
Home-page: https://github.com/hookery
Author: csy
Author-email: c826456327@gmail.com
License: UNKNOWN
Platform: UNKNOWN
